pypixelcolor/__init__.py
pypixelcolor/__main__.py
pypixelcolor/__version__.py
pypixelcolor/cli.py
pypixelcolor/client.py
pypixelcolor/client.pyi
pypixelcolor/websocket.py
pypixelcolor/commands/__init__.py
pypixelcolor/commands/clear.py
pypixelcolor/commands/delete.py
pypixelcolor/commands/send_image.py
pypixelcolor/commands/set_brightness.py
pypixelcolor/commands/set_clock_mode.py
pypixelcolor/commands/set_fun_mode.py
pypixelcolor/commands/set_orientation.py
pypixelcolor/commands/set_power.py
pypixelcolor/commands/set_rhythm_mode.py
pypixelcolor/commands/set_time.py
pypixelcolor/commands/show_slot.py
pypixelcolor/commands/send_text/__init__.py
pypixelcolor/commands/send_text/encoding.py
pypixelcolor/commands/send_text/font_utils.py
pypixelcolor/commands/send_text/image_processing.py
pypixelcolor/commands/send_text/models.py
pypixelcolor/fonts/CUSONG.json
pypixelcolor/fonts/CUSONG.ttf
pypixelcolor/fonts/SIMSUN.json
pypixelcolor/fonts/SIMSUN.ttf
pypixelcolor/fonts/VCR_OSD_MONO.json
pypixelcolor/fonts/VCR_OSD_MONO.ttf
pypixelcolor/lib/__init__.py
pypixelcolor/lib/command_result.py
pypixelcolor/lib/constants.py
pypixelcolor/lib/device_info.py
pypixelcolor/lib/device_session.py
pypixelcolor/lib/emoji_manager.py
pypixelcolor/lib/font_config.py
pypixelcolor/lib/internal_commands.py
pypixelcolor/lib/logging.py
pypixelcolor/lib/transport/__init__.py
pypixelcolor/lib/transport/ack_manager.py
pypixelcolor/lib/transport/send_plan.py
pypixelcolor/lib/transport/window.py
pypixelcolor-0.4.0.dist-info/METADATA
pypixelcolor-0.4.0.dist-info/WHEEL
pypixelcolor-0.4.0.dist-info/entry_points.txt
pypixelcolor-0.4.0.dist-info/licenses/LICENSE.md
pypixelcolor-0.4.0.dist-info/RECORD
