Metadata-Version: 2.4
Name: pypixelcolor
Version: 0.4.0
Summary: A Python library to control iPixel Color devices.
Project-URL: Homepage, https://github.com/lucagoc/pypixelcolor
Project-URL: Issues, https://github.com/lucagoc/pypixelcolor/issues
Author-email: Lucas Balmès <lucagoc@pm.me>
License-Expression: MIT
License-File: LICENSE.md
Classifier: Operating System :: OS Independent
Classifier: Programming Language :: Python :: 3
Requires-Python: >=3.9
Requires-Dist: bleak
Requires-Dist: crccheck
Requires-Dist: pillow
Requires-Dist: websockets
Provides-Extra: dev
Requires-Dist: mike; extra == 'dev'
Requires-Dist: mkdocs-material; extra == 'dev'
Requires-Dist: mkdocs-static-i18n; extra == 'dev'
Requires-Dist: mkdocstrings[python]; extra == 'dev'
Requires-Dist: pytest-cov>=4.0.0; extra == 'dev'
Requires-Dist: pytest>=7.0.0; extra == 'dev'
Provides-Extra: extra
Requires-Dist: pillow-heif>=1.0.0; extra == 'extra'
